passg/__init__.py
passg/passg.py
passg/py.typed
passg-1.2.dist-info/licenses/LICENSE
passg-1.2.dist-info/METADATA
passg-1.2.dist-info/WHEEL
passg-1.2.dist-info/top_level.txt
passg-1.2.dist-info/RECORD
