Metadata-Version: 2.4
Name: passg
Version: 1.2
Summary: strong password generator
Home-page: https://github.com/yasin1ar/passg
Author: Yasin Amirany
Author-email: yasin.amirany@gmail.com
License: MIT
Classifier: Programming Language :: Python :: 3
Classifier: License :: OSI Approved :: MIT License
Classifier: Operating System :: OS Independent
Requires-Python: >=3.6
License-File: LICENSE
Dynamic: author
Dynamic: author-email
Dynamic: classifier
Dynamic: description
Dynamic: description-content-type
Dynamic: home-page
Dynamic: license
Dynamic: license-file
Dynamic: requires-python
Dynamic: summary
